ultima_scraper_db/__init__.py
ultima_scraper_db/databases/__init__.py
ultima_scraper_db/databases/rest_api.py
ultima_scraper_db/databases/ultima_archive/__init__.py
ultima_scraper_db/databases/ultima_archive/alembic/README
ultima_scraper_db/databases/ultima_archive/alembic/env.py
ultima_scraper_db/databases/ultima_archive/alembic/script.py.mako
ultima_scraper_db/databases/ultima_archive/alembic/versions/358d71fc1759_.py
ultima_scraper_db/databases/ultima_archive/alembic/versions/ac840f4e3061_.py
ultima_scraper_db/databases/ultima_archive/alembic.ini
ultima_scraper_db/databases/ultima_archive/api/__init__.py
ultima_scraper_db/databases/ultima_archive/api/app.py
ultima_scraper_db/databases/ultima_archive/api/client.py
ultima_scraper_db/databases/ultima_archive/api/main.py
ultima_scraper_db/databases/ultima_archive/api/routers/__init__.py
ultima_scraper_db/databases/ultima_archive/api/routers/client.py
ultima_scraper_db/databases/ultima_archive/api/routers/filepaths.py
ultima_scraper_db/databases/ultima_archive/api/routers/files.py
ultima_scraper_db/databases/ultima_archive/api/routers/hosts.py
ultima_scraper_db/databases/ultima_archive/api/routers/jobs.py
ultima_scraper_db/databases/ultima_archive/api/routers/media.py
ultima_scraper_db/databases/ultima_archive/api/routers/media_detections.py
ultima_scraper_db/databases/ultima_archive/api/routers/notifications.py
ultima_scraper_db/databases/ultima_archive/api/routers/remote_urls.py
ultima_scraper_db/databases/ultima_archive/api/routers/search.py
ultima_scraper_db/databases/ultima_archive/api/routers/sites.py
ultima_scraper_db/databases/ultima_archive/api/routers/users.py
ultima_scraper_db/databases/ultima_archive/database_api.py
ultima_scraper_db/databases/ultima_archive/filters.py
ultima_scraper_db/databases/ultima_archive/management_api.py
ultima_scraper_db/databases/ultima_archive/schemas/__init__.py
ultima_scraper_db/databases/ultima_archive/schemas/management.py
ultima_scraper_db-0.4.22.dist-info/LICENSE
ultima_scraper_db-0.4.22.dist-info/METADATA
ultima_scraper_db-0.4.22.dist-info/WHEEL
ultima_scraper_db-0.4.22.dist-info/RECORD
