Metadata-Version: 2.3
Name: ultima-scraper-db
Version: 0.4.22
Summary: 
Author: UltimaHoarder
Author-email: 1285176+UltimaHoarder@users.noreply.github.com
Requires-Python: >=3.10,<4
Classifier: Programming Language :: Python :: 3
Classifier: Programming Language :: Python :: 3.10
Classifier: Programming Language :: Python :: 3.11
Classifier: Programming Language :: Python :: 3.12
Classifier: Programming Language :: Python :: 3.13
Requires-Dist: alembic (>=1.11.1,<2.0.0)
Requires-Dist: alembic-postgresql-enum (>=1.7.0,<2.0.0)
Requires-Dist: asyncpg (>=0.30.0,<0.31.0)
Requires-Dist: fastapi (>=0.100.0,<1.0.0)
Requires-Dist: fastapi-pagination (>=0.12.6,<0.13.0)
Requires-Dist: gunicorn (>=23.0.0,<24.0.0)
Requires-Dist: inflection (>=0.5.1,<0.6.0)
Requires-Dist: platformdirs (>=4.2.2,<5.0.0)
Requires-Dist: psycopg (>=3.1.9,<4.0.0)
Requires-Dist: redis (>=6.2.0,<7.0.0)
Requires-Dist: slowapi (>=0.1.9,<0.2.0)
Requires-Dist: sqlalchemy-utils (>=0.41.1,<0.42.0)
Requires-Dist: sqlalchemy[asyncio] (>=2.0.16,<3.0.0)
Requires-Dist: sshtunnel (>=0.4.0,<0.5.0)
Requires-Dist: ultima-scraper-api (>=2.0.0,<3.0.0)
Requires-Dist: ultima-scraper-collection (>=2.0.0,<3.0.0)
Requires-Dist: uvicorn[standard] (>=0.25.0,<0.26.0)
